singular_api_client/__init__.py
singular_api_client/exceptions.py
singular_api_client/helpers.py
singular_api_client/params.py
singular_api_client/singular_client.py
singular_api_client/version.py
singular_api_client-0.7.4.dist-info/LICENSE.txt
singular_api_client-0.7.4.dist-info/METADATA
singular_api_client-0.7.4.dist-info/WHEEL
singular_api_client-0.7.4.dist-info/top_level.txt
singular_api_client-0.7.4.dist-info/RECORD
