Metadata-Version: 2.1
Name: singular-api-client
Version: 0.7.4
Summary: Helper Library to use Singular Reporting API
Home-page: https://github.com/singular-labs/singular_api_client/
Author: Singular Labs, Inc
Author-email: devs@singular.net
License: Apache
Download-URL: https://github.com/singular-labs/singular_api_client/tarball/0.7.4
Project-URL: Documentation, https://github.com/singular-labs/singular_api_client
Project-URL: Source, https://github.com/singular-labs/singular_api_client
Project-URL: Tracker, https://github.com/singular-labs/singular_api_client/issues
Keywords: singular
Platform: UNKNOWN
Classifier: Programming Language :: Python
Classifier: Programming Language :: Python :: 2.7
Classifier: Programming Language :: Python :: 3
Classifier: Programming Language :: Python :: 3.6
Classifier: Programming Language :: Python :: 3.7
Classifier: Programming Language :: Python :: 3.8
License-File: LICENSE.txt
Requires-Dist: requests
Requires-Dist: pytz
Requires-Dist: retrying
Requires-Dist: futures; python_version == "2.7"
